setup.py
gash/__init__.py
gash/crypt3des.py
gash/gash_helper.py
gash/utils.py
gash.egg-info/PKG-INFO
gash.egg-info/SOURCES.txt
gash.egg-info/dependency_links.txt
gash.egg-info/entry_points.txt
gash.egg-info/not-zip-safe
gash.egg-info/requires.txt
gash.egg-info/top_level.txt