Metadata-Version: 1.0
Name: gash
Version: 0.1.8
Summary: gash client in python
Home-page: https://github.com/dantezhu/gash
Author: dantezhu
Author-email: zny2008@gmail.com
License: UNKNOWN
Platform: UNKNOWN
